README.txt
setup.cfg
setup.py
twodeg/__init__.py
twodeg.recipe.apacheconf.egg-info/PKG-INFO
twodeg.recipe.apacheconf.egg-info/SOURCES.txt
twodeg.recipe.apacheconf.egg-info/dependency_links.txt
twodeg.recipe.apacheconf.egg-info/entry_points.txt
twodeg.recipe.apacheconf.egg-info/namespace_packages.txt
twodeg.recipe.apacheconf.egg-info/requires.txt
twodeg.recipe.apacheconf.egg-info/top_level.txt
twodeg.recipe.apacheconf.egg-info/zip-safe
twodeg/recipe/__init__.py
twodeg/recipe/apacheconf/__init__.py
twodeg/recipe/apacheconf/recipe.py
twodeg/recipe/apacheconf/tests/__init__.py
twodeg/recipe/apacheconf/tests/test_docs.py