Metadata-Version: 1.0
Name: twodeg.recipe.apacheconf
Version: 0.1dev
Summary: An apache VirtualHost config generator
Home-page: UNKNOWN
Author: Ben Ford
Author-email: ben.fordnz@gmail.com
License: GPL
Platform: UNKNOWN
Classifier: Framework :: Buildout
Classifier: Intended Audience :: Developers
Classifier: Topic :: Software Development :: Build Tools
Classifier: Topic :: Software Development :: Libraries :: Python Modules
Classifier: License :: OSI Approved :: GNU General Public License (GPL)
